biggo_mcp_server/__init__.py
biggo_mcp_server/lib/__init__.py
biggo_mcp_server/lib/access_token.py
biggo_mcp_server/lib/alive_checker.py
biggo_mcp_server/lib/log.py
biggo_mcp_server/lib/server.py
biggo_mcp_server/lib/server_setup.py
biggo_mcp_server/lib/utils.py
biggo_mcp_server/services/__init__.py
biggo_mcp_server/services/price_history.py
biggo_mcp_server/services/product_search.py
biggo_mcp_server/services/spec_search.py
biggo_mcp_server/tools/__init__.py
biggo_mcp_server/tools/price_history.py
biggo_mcp_server/tools/product_search.py
biggo_mcp_server/tools/spec_search.py
biggo_mcp_server/types/__init__.py
biggo_mcp_server/types/responses.py
biggo_mcp_server/types/setting.py
biggo_mcp_server/types/api_ret/__init__.py
biggo_mcp_server/types/api_ret/auth_token.py
biggo_mcp_server/types/api_ret/common.py
biggo_mcp_server/types/api_ret/ec_list.py
biggo_mcp_server/types/api_ret/ninde_from_url.py
biggo_mcp_server/types/api_ret/price_history.py
biggo_mcp_server/types/api_ret/product_search.py
biggo_mcp_server/types/api_ret/short_link.py
biggo_mcp_server/types/api_ret/spec.py
biggo_mcp_server-0.2.0.dist-info/METADATA
biggo_mcp_server-0.2.0.dist-info/WHEEL
biggo_mcp_server-0.2.0.dist-info/entry_points.txt
biggo_mcp_server-0.2.0.dist-info/licenses/LICENSE
biggo_mcp_server-0.2.0.dist-info/RECORD
